pysolaar/__init__.py
pysolaar/document.py
pysolaar/pysolaar.py
pysolaar/queryset.py
pysolaar/result.py
pysolaar/utils/__init__.py
pysolaar/utils/camel_to_snake.py
pysolaar/utils/chunks.py
pysolaar/utils/encoders_and_decoders.py
pysolaar/utils/exceptions.py
pysolaar/utils/meta_utils.py
pysolaar-0.8.0.dist-info/WHEEL
pysolaar-0.8.0.dist-info/METADATA
pysolaar-0.8.0.dist-info/RECORD
