Metadata-Version: 2.1
Name: pysolaar
Version: 0.8.0
Summary: 
Author: Richard Hadden
Author-email: richard.hadden@oeaw.ac.at
Requires-Python: >=3.6,<4
Classifier: Programming Language :: Python :: 3
Classifier: Programming Language :: Python :: 3.6
Classifier: Programming Language :: Python :: 3.7
Classifier: Programming Language :: Python :: 3.8
Classifier: Programming Language :: Python :: 3.9
Requires-Dist: pysolr (>=3.9.0,<4.0.0)
Requires-Dist: solrq (>=1.1.1,<2.0.0)
